apyproxy/__init__.py
apyproxy-0.2.2.dist-info/LICENSE
apyproxy-0.2.2.dist-info/METADATA
apyproxy-0.2.2.dist-info/WHEEL
apyproxy-0.2.2.dist-info/RECORD
